Metadata-Version: 2.2
Name: nonebot_plugin_baisuwen
Version: 1.1.0
Summary: 基于DeepSeek的智能聊天机器人，打造属于你的赛博群友
Home-page: https://github.com/Longxuanyue/nonebot_plugin_baisuwen
Author: LongYue
Author-email: 2279303156@qq.com
Classifier: Programming Language :: Python :: 3
Classifier: License :: OSI Approved :: MIT License
Classifier: Operating System :: OS Independent
Requires-Python: >=3.8
License-File: LICENSE
Requires-Dist: nonebot2>=2.0.0
Requires-Dist: nonebot-adapter-onebot-v11
Requires-Dist: httpx>=0.23.0
Requires-Dist: tenacity>=8.2.2
Requires-Dist: redis>=4.5.1
Requires-Dist: python-dotenv>=0.21.0
Requires-Dist: msgpack>=1.0.5
Provides-Extra: dev
Requires-Dist: pytest>=7.0; extra == "dev"
Requires-Dist: pytest-asyncio>=0.21.0; extra == "dev"
Requires-Dist: black>=23.3.0; extra == "dev"
Requires-Dist: mypy>=1.3.0; extra == "dev"
Dynamic: author
Dynamic: author-email
Dynamic: classifier
Dynamic: description
Dynamic: description-content-type
Dynamic: home-page
Dynamic: provides-extra
Dynamic: requires-dist
Dynamic: requires-python
Dynamic: summary
